{
  "1": [
    [
      {
        "mark": "bar",
        "encoding": {
          "x": {
            "type": "nominal",
            "interesting": true,
            "field": "n1",
            "channel": "x"
          }
        }
      },
      {
        "mark": "bar",
        "encoding": {
          "y": {
            "type": "nominal",
            "interesting": true,
            "field": "n1",
            "channel": "y"
          }
        }
      }
    ],
    [
      {
        "mark": "point",
        "encoding": {
          "x": {
            "aggregate": "min",
            "type": "ordinal",
            "interesting": true,
            "field": "o1",
            "channel": "x"
          }
        }
      },
      {
        "mark": "point",
        "encoding": {
          "y": {
            "aggregate": "min",
            "type": "ordinal",
            "interesting": true,
            "field": "o1",
            "channel": "y"
          }
        }
      }
    ]
  ],
  "2": [
    [
      {
        "mark": "tick",
        "encoding": {
          "x": {
            "type": "quantitative",
            "interesting": true,
            "field": "q1",
            "channel": "x"
          },
          "y": {
            "type": "nominal",
            "field": "n1",
            "channel": "y"
          }
        }
      },
      {
        "mark": "tick",
        "encoding": {
          "x": {
            "type": "quantitative",
            "interesting": true,
            "field": "q1",
            "channel": "x"
          },
          "y": {
            "type": "nominal",
            "field": "n1",
            "channel": "y"
          }
        }
      },
      {
        "mark": "tick",
        "encoding": {
          "color": {
            "type": "quantitative",
            "interesting": true,
            "field": "q1",
            "channel": "color"
          },
          "y": {
            "type": "nominal",
            "field": "n1",
            "channel": "y"
          }
        }
      },
      {
        "mark": "tick",
        "encoding": {
          "x": {
            "type": "quantitative",
            "interesting": true,
            "field": "q1",
            "channel": "x"
          },
          "column": {
            "type": "nominal",
            "field": "n1",
            "channel": "column"
          }
        }
      }
    ],
    [
      {
        "mark": "point",
        "encoding": {
          "x": {
            "type": "temporal",
            "interesting": true,
            "field": "t1",
            "channel": "x"
          },
          "y": {
            "type": "temporal",
            "field": "t2",
            "channel": "y"
          }
        }
      },
      {
        "mark": "point",
        "encoding": {
          "x": {
            "type": "temporal",
            "interesting": true,
            "field": "t1",
            "channel": "x"
          },
          "y": {
            "type": "temporal",
            "field": "t2",
            "channel": "y"
          }
        }
      },
      {
        "mark": "point",
        "encoding": {
          "color": {
            "type": "temporal",
            "interesting": true,
            "field": "t1",
            "channel": "color"
          },
          "y": {
            "type": "temporal",
            "field": "t2",
            "channel": "y"
          }
        }
      },
      {
        "mark": "point",
        "encoding": {
          "x": {
            "type": "temporal",
            "interesting": true,
            "field": "t1",
            "channel": "x"
          },
          "opacity": {
            "type": "temporal",
            "field": "t2",
            "channel": "opacity"
          }
        }
      },
      {
        "mark": "point",
        "encoding": {
          "x": {
            "type": "temporal",
            "interesting": true,
            "field": "t1",
            "channel": "x"
          },
          "size": {
            "type": "temporal",
            "field": "t2",
            "channel": "size"
          }
        }
      }
    ]
  ],
  "3": [
    [
      {
        "mark": "rule",
        "encoding": {
          "x": {
            "stack": null,
            "type": "nominal",
            "field": "n1",
            "channel": "x"
          },
          "opacity": {
            "type": "quantitative",
            "interesting": true,
            "field": "q1",
            "channel": "opacity"
          },
          "color": {
            "type": "nominal",
            "field": "n2",
            "channel": "color"
          }
        }
      },
      {
        "mark": "rule",
        "encoding": {
          "x": {
            "stack": null,
            "type": "nominal",
            "field": "n1",
            "channel": "x"
          },
          "size": {
            "type": "quantitative",
            "interesting": true,
            "field": "q1",
            "channel": "size"
          },
          "color": {
            "type": "nominal",
            "field": "n2",
            "channel": "color"
          }
        }
      },
      {
        "mark": "rule",
        "encoding": {
          "column": {
            "stack": null,
            "type": "nominal",
            "field": "n1",
            "channel": "column"
          },
          "y": {
            "type": "quantitative",
            "interesting": true,
            "field": "q1",
            "channel": "y"
          },
          "color": {
            "type": "nominal",
            "field": "n2",
            "channel": "color"
          }
        }
      }
    ],
    [
      {
        "mark": "point",
        "encoding": {
          "x": {
            "type": "nominal",
            "field": "n1",
            "channel": "x"
          },
          "size": {
            "sort": "descending",
            "type": "quantitative",
            "interesting": true,
            "field": "q1",
            "channel": "size"
          },
          "color": {
            "type": "nominal",
            "field": "n2",
            "channel": "color"
          }
        }
      },
      {
        "mark": "point",
        "encoding": {
          "x": {
            "type": "nominal",
            "field": "n1",
            "channel": "x"
          },
          "y": {
            "sort": "descending",
            "type": "quantitative",
            "interesting": true,
            "field": "q1",
            "channel": "y"
          },
          "color": {
            "type": "nominal",
            "field": "n2",
            "channel": "color"
          }
        }
      },
      {
        "mark": "point",
        "encoding": {
          "x": {
            "type": "nominal",
            "field": "n1",
            "channel": "x"
          },
          "size": {
            "sort": "descending",
            "type": "quantitative",
            "interesting": true,
            "field": "q1",
            "channel": "size"
          },
          "color": {
            "type": "nominal",
            "field": "n2",
            "channel": "color"
          }
        }
      },
      {
        "mark": "point",
        "encoding": {
          "x": {
            "type": "nominal",
            "field": "n1",
            "channel": "x"
          },
          "opacity": {
            "sort": "descending",
            "type": "quantitative",
            "interesting": true,
            "field": "q1",
            "channel": "opacity"
          },
          "color": {
            "type": "nominal",
            "field": "n2",
            "channel": "color"
          }
        }
      },
      {
        "mark": "point",
        "encoding": {
          "x": {
            "type": "nominal",
            "field": "n1",
            "channel": "x"
          },
          "size": {
            "sort": "descending",
            "type": "quantitative",
            "interesting": true,
            "field": "q1",
            "channel": "size"
          },
          "color": {
            "type": "nominal",
            "field": "n2",
            "channel": "color"
          }
        }
      },
      {
        "mark": "point",
        "encoding": {
          "x": {
            "type": "nominal",
            "field": "n1",
            "channel": "x"
          },
          "size": {
            "sort": "descending",
            "type": "quantitative",
            "interesting": true,
            "field": "q1",
            "channel": "size"
          },
          "shape": {
            "type": "nominal",
            "field": "n2",
            "channel": "shape"
          }
        }
      }
    ]
  ],
  "4": [
    [
      {
        "mark": "point",
        "encoding": {
          "x": {
            "type": "nominal",
            "field": "n1",
            "channel": "x"
          },
          "y": {
            "stack": "normalize",
            "bin": {
              "maxbins": 3
            },
            "type": "quantitative",
            "interesting": true,
            "field": "q1",
            "channel": "y"
          },
          "shape": {
            "sort": "descending",
            "type": "nominal",
            "field": "n2",
            "channel": "shape"
          },
          "color": {
            "bin": {
              "maxbins": 10
            },
            "type": "quantitative",
            "field": "q2",
            "channel": "color"
          }
        }
      },
      {
        "mark": "point",
        "encoding": {
          "x": {
            "type": "nominal",
            "field": "n1",
            "channel": "x"
          },
          "y": {
            "stack": "normalize",
            "bin": {
              "maxbins": 3
            },
            "type": "quantitative",
            "interesting": true,
            "field": "q1",
            "channel": "y"
          },
          "shape": {
            "sort": "descending",
            "type": "nominal",
            "field": "n2",
            "channel": "shape"
          },
          "opacity": {
            "bin": {
              "maxbins": 10
            },
            "type": "quantitative",
            "field": "q2",
            "channel": "opacity"
          }
        }
      }
    ],
    [
      {
        "mark": "point",
        "encoding": {
          "y": {
            "type": "temporal",
            "interesting": true,
            "field": "t1",
            "channel": "y"
          },
          "x": {
            "type": "nominal",
            "field": "n1",
            "channel": "x"
          },
          "shape": {
            "type": "nominal",
            "field": "n2",
            "channel": "shape"
          },
          "color": {
            "type": "quantitative",
            "field": "q1",
            "channel": "color"
          }
        }
      },
      {
        "mark": "point",
        "encoding": {
          "y": {
            "type": "temporal",
            "interesting": true,
            "field": "t1",
            "channel": "y"
          },
          "x": {
            "type": "nominal",
            "field": "n1",
            "channel": "x"
          },
          "shape": {
            "type": "nominal",
            "field": "n2",
            "channel": "shape"
          },
          "color": {
            "type": "quantitative",
            "field": "q1",
            "channel": "color"
          }
        }
      },
      {
        "mark": "point",
        "encoding": {
          "y": {
            "type": "temporal",
            "interesting": true,
            "field": "t1",
            "channel": "y"
          },
          "x": {
            "type": "nominal",
            "field": "n1",
            "channel": "x"
          },
          "shape": {
            "type": "nominal",
            "field": "n2",
            "channel": "shape"
          },
          "color": {
            "type": "quantitative",
            "field": "q1",
            "channel": "color"
          }
        }
      },
      {
        "mark": "point",
        "encoding": {
          "size": {
            "type": "temporal",
            "interesting": true,
            "field": "t1",
            "channel": "size"
          },
          "x": {
            "type": "nominal",
            "field": "n1",
            "channel": "x"
          },
          "shape": {
            "type": "nominal",
            "field": "n2",
            "channel": "shape"
          },
          "color": {
            "type": "quantitative",
            "field": "q1",
            "channel": "color"
          }
        }
      },
      {
        "mark": "point",
        "encoding": {
          "y": {
            "type": "temporal",
            "interesting": true,
            "field": "t1",
            "channel": "y"
          },
          "x": {
            "type": "nominal",
            "field": "n1",
            "channel": "x"
          },
          "shape": {
            "type": "nominal",
            "field": "n2",
            "channel": "shape"
          },
          "color": {
            "type": "quantitative",
            "field": "q1",
            "channel": "color"
          }
        }
      },
      {
        "mark": "point",
        "encoding": {
          "y": {
            "type": "temporal",
            "interesting": true,
            "field": "t1",
            "channel": "y"
          },
          "x": {
            "type": "nominal",
            "field": "n1",
            "channel": "x"
          },
          "row": {
            "type": "nominal",
            "field": "n2",
            "channel": "row"
          },
          "color": {
            "type": "quantitative",
            "field": "q1",
            "channel": "color"
          }
        }
      }
    ]
  ]
}