{
    "mark": "point",
    "encodings": [
        {
            "channel": "color",
            "field": "q1",
            "type": "quantitative"
        },
        {
            "channel": "?",
            "field": "q2",
            "type": "quantitative"
        },
        {
            "channel": "x",
            "field": "n",
            "type": "nominal",
            "bin": {
                "maxbins": "?"
            }
        }
    ],
    "data": {
        "values": [
            {
                "n": 1,
                "q1": 67.84931808027038,
                "q2": 58.340354403768785
            },
            {
                "n": 1,
                "q1": 59.72308453166506,
                "q2": 38.14600343205611
            },
            {
                "n": 0,
                "q1": 7.1268225071839435,
                "q2": 7.383488661249701
            },
            {
                "n": 2,
                "q1": 46.49769050234053,
                "q2": 14.356873265896509
            },
            {
                "n": 1,
                "q1": 54.61079254162226,
                "q2": 6.656959636993759
            },
            {
                "n": 1,
                "q1": 55.78121404818775,
                "q2": 16.91243454914413
            },
            {
                "n": 1,
                "q1": 85.64717308551708,
                "q2": 26.9352122500533
            },
            {
                "n": 1,
                "q1": 8.989177336844076,
                "q2": 17.370321539593498
            },
            {
                "n": 2,
                "q1": 30.759535710716598,
                "q2": 30.574188387592404
            },
            {
                "n": 0,
                "q1": 0.5978116802541633,
                "q2": 45.14430468174445
            },
            {
                "n": 0,
                "q1": 47.35868098951434,
                "q2": 48.08383036397889
            },
            {
                "n": 1,
                "q1": 39.16001430930469,
                "q2": 59.65385294452847
            },
            {
                "n": 0,
                "q1": 62.96756886144718,
                "q2": 75.24928957185712
            },
            {
                "n": 2,
                "q1": 1.5147719079137645,
                "q2": 42.160587068459584
            },
            {
                "n": 2,
                "q1": 75.46430819088765,
                "q2": 40.73891926501799
            },
            {
                "n": 0,
                "q1": 65.24254446948997,
                "q2": 64.85231861051257
            },
            {
                "n": 0,
                "q1": 19.458677608791184,
                "q2": 54.993331675259576
            },
            {
                "n": 1,
                "q1": 36.96708622854181,
                "q2": 86.11827810554041
            },
            {
                "n": 1,
                "q1": 51.731020386829776,
                "q2": 7.2218180181938765
            },
            {
                "n": 2,
                "q1": 80.50414800071569,
                "q2": 64.24692544078033
            },
            {
                "n": 0,
                "q1": 89.37586060447323,
                "q2": 60.00335461030373
            },
            {
                "n": 1,
                "q1": 36.628721148641084,
                "q2": 72.68268274528349
            },
            {
                "n": 1,
                "q1": 38.11801707330182,
                "q2": 10.482493344485547
            },
            {
                "n": 0,
                "q1": 38.511218635367264,
                "q2": 44.02531756331027
            },
            {
                "n": 1,
                "q1": 70.71386128291633,
                "q2": 10.165280665730114
            },
            {
                "n": 2,
                "q1": 24.2171274758167,
                "q2": 14.712022882824794
            },
            {
                "n": 2,
                "q1": 82.33588337525605,
                "q2": 1.8224789153005527
            },
            {
                "n": 1,
                "q1": 17.516631710368596,
                "q2": 12.254768676897497
            },
            {
                "n": 2,
                "q1": 58.33398221415286,
                "q2": 55.97684304539678
            },
            {
                "n": 2,
                "q1": 8.657195841912296,
                "q2": 6.307102607604675
            },
            {
                "n": 2,
                "q1": 41.19875532252479,
                "q2": 81.87913568598333
            },
            {
                "n": 2,
                "q1": 88.2221310270227,
                "q2": 67.7139473870491
            },
            {
                "n": 1,
                "q1": 36.773095937634054,
                "q2": 54.13923271730845
            },
            {
                "n": 1,
                "q1": 11.882606060435831,
                "q2": 26.645886006695928
            },
            {
                "n": 2,
                "q1": 86.88923870676336,
                "q2": 7.749240715480065
            },
            {
                "n": 2,
                "q1": 20.3322305152404,
                "q2": 73.39413159571542
            },
            {
                "n": 1,
                "q1": 57.68959061907373,
                "q2": 60.795567821900626
            },
            {
                "n": 0,
                "q1": 65.56882096481603,
                "q2": 59.09857664048236
            },
            {
                "n": 1,
                "q1": 16.932719722254507,
                "q2": 20.434618267745915
            },
            {
                "n": 2,
                "q1": 76.86361292691487,
                "q2": 10.680202598130116
            },
            {
                "n": 2,
                "q1": 39.01870898203914,
                "q2": 52.45921349501394
            },
            {
                "n": 2,
                "q1": 38.39877907700736,
                "q2": 8.044235822193652
            },
            {
                "n": 1,
                "q1": 22.838906657435246,
                "q2": 41.94198149154773
            },
            {
                "n": 0,
                "q1": 55.867796415466344,
                "q2": 34.37550559682152
            },
            {
                "n": 2,
                "q1": 26.268882433812767,
                "q2": 47.54623327427308
            },
            {
                "n": 0,
                "q1": 9.176858553214833,
                "q2": 8.473871432195107
            },
            {
                "n": 1,
                "q1": 72.16784656210201,
                "q2": 68.5342031715187
            },
            {
                "n": 0,
                "q1": 28.490798138497247,
                "q2": 28.33167110621703
            },
            {
                "n": 2,
                "q1": 6.093270685685605,
                "q2": 76.10404594957731
            },
            {
                "n": 1,
                "q1": 10.785689871340594,
                "q2": 12.354261528121198
            },
            {
                "n": 0,
                "q1": 88.1907885715044,
                "q2": 26.22568079182286
            },
            {
                "n": 1,
                "q1": 47.036575632577865,
                "q2": 25.903581371188253
            },
            {
                "n": 2,
                "q1": 78.37592530964343,
                "q2": 13.263946846741131
            },
            {
                "n": 0,
                "q1": 45.91889256499373,
                "q2": 74.74680054615112
            },
            {
                "n": 1,
                "q1": 59.2510617473011,
                "q2": 40.52614982456727
            },
            {
                "n": 2,
                "q1": 29.857050808873694,
                "q2": 13.32976318137103
            },
            {
                "n": 2,
                "q1": 62.38037448224871,
                "q2": 81.75945592832682
            },
            {
                "n": 0,
                "q1": 13.714465921526616,
                "q2": 3.029810995267601
            },
            {
                "n": 1,
                "q1": 77.48724839541391,
                "q2": 34.85139365887497
            },
            {
                "n": 1,
                "q1": 45.09583090774595,
                "q2": 59.62698080545242
            },
            {
                "n": 1,
                "q1": 82.42948808764692,
                "q2": 17.890883466996424
            },
            {
                "n": 2,
                "q1": 86.54483347859285,
                "q2": 85.64799943923911
            },
            {
                "n": 0,
                "q1": 79.91709867021872,
                "q2": 64.79459959149044
            },
            {
                "n": 0,
                "q1": 49.64518569116572,
                "q2": 79.00416741453208
            },
            {
                "n": 0,
                "q1": 25.890537179133112,
                "q2": 19.47148055189108
            },
            {
                "n": 1,
                "q1": 41.726902574133256,
                "q2": 67.8478634473251
            },
            {
                "n": 2,
                "q1": 68.77483386356278,
                "q2": 6.245686632497785
            },
            {
                "n": 2,
                "q1": 63.086231851191556,
                "q2": 39.07864617805098
            },
            {
                "n": 0,
                "q1": 11.3182309159085,
                "q2": 77.67535312933606
            },
            {
                "n": 1,
                "q1": 85.4200525589939,
                "q2": 36.05365344176171
            },
            {
                "n": 0,
                "q1": 78.80794631472986,
                "q2": 31.976796244031597
            },
            {
                "n": 0,
                "q1": 68.23168043432445,
                "q2": 89.51726179670726
            },
            {
                "n": 0,
                "q1": 77.42878561203663,
                "q2": 42.659367234570446
            },
            {
                "n": 1,
                "q1": 69.4542179131816,
                "q2": 24.614510785656122
            },
            {
                "n": 1,
                "q1": 64.9921609060255,
                "q2": 48.63883534847254
            },
            {
                "n": 1,
                "q1": 49.76228803413736,
                "q2": 81.32072368086365
            },
            {
                "n": 1,
                "q1": 14.366589268212655,
                "q2": 41.522739998325974
            },
            {
                "n": 0,
                "q1": 76.01311009256155,
                "q2": 72.88820282250727
            },
            {
                "n": 2,
                "q1": 56.12567049580125,
                "q2": 60.474935769247736
            },
            {
                "n": 1,
                "q1": 18.660773548126567,
                "q2": 3.139818387953736
            },
            {
                "n": 1,
                "q1": 52.41170116298117,
                "q2": 21.763881954446063
            },
            {
                "n": 2,
                "q1": 51.28814842926619,
                "q2": 21.76343992717278
            },
            {
                "n": 0,
                "q1": 24.482671210435687,
                "q2": 69.76509562974441
            },
            {
                "n": 2,
                "q1": 30.31603248496745,
                "q2": 21.338888918044006
            },
            {
                "n": 1,
                "q1": 66.17171667167919,
                "q2": 83.02372480490881
            },
            {
                "n": 1,
                "q1": 76.56191958945533,
                "q2": 43.81308680692981
            },
            {
                "n": 1,
                "q1": 80.13863905179824,
                "q2": 22.044190826534685
            },
            {
                "n": 2,
                "q1": 30.924516868457726,
                "q2": 68.91786625279566
            },
            {
                "n": 2,
                "q1": 80.01806232841587,
                "q2": 42.235418268546866
            },
            {
                "n": 2,
                "q1": 82.22127818139751,
                "q2": 81.87981915124044
            }
        ]
    }
}